drmeter/__init__.py
drmeter/__main__.py
drmeter/algorithm.py
drmeter/cli.py
drmeter/compat.py
drmeter/exceptions.py
drmeter/models.py
drmeter/utils.py
drmeter-0.3.2.dist-info/LICENSE
drmeter-0.3.2.dist-info/METADATA
drmeter-0.3.2.dist-info/WHEEL
drmeter-0.3.2.dist-info/entry_points.txt
drmeter-0.3.2.dist-info/RECORD
