Metadata-Version: 2.1
Name: drmeter
Version: 0.3.2
Summary: Dynamic Range (DR) algorithm implementation in python
Home-page: https://github.com/janw/drmeter
License: MIT
Author: Jan Willhaus
Author-email: mail@janwillhaus.de
Requires-Python: >=3.9,<4.0
Classifier: License :: OSI Approved :: MIT License
Classifier: Programming Language :: Python :: 3
Classifier: Programming Language :: Python :: 3.9
Classifier: Programming Language :: Python :: 3.10
Classifier: Programming Language :: Python :: 3.11
Classifier: Programming Language :: Python :: 3.12
Requires-Dist: numpy (>=2,<3)
Requires-Dist: rich (>=13,<14)
Requires-Dist: rich-click (>=1,<2)
Requires-Dist: soundfile (>=0.12.1,<0.13.0)
Project-URL: Repository, https://github.com/janw/drmeter
